{
  "WARN_DOL": {
    "ok": false,
    "detail": "HTTP 403",
    "ts": "2026-04-17T06:23:01.783430"
  },
  "WARN_CA": {
    "ok": true,
    "detail": "HTTP 200",
    "ts": "2026-04-17T06:23:02.878206"
  },
  "OFAC": {
    "ok": false,
    "detail": "HTTPSConnectionPool(host='www.treasury.gov', port=443): Read timed out. (read timeout=20)",
    "ts": "2026-04-17T06:23:24.044346"
  },
  "USASPENDING": {
    "ok": true,
    "detail": "",
    "ts": "2026-04-17T06:23:24.527568"
  },
  "USPTO_quantum co": {
    "ok": false,
    "detail": "HTTP 410",
    "ts": "2026-04-17T06:23:24.738043"
  },
  "USPTO_hypersonic": {
    "ok": false,
    "detail": "HTTP 410",
    "ts": "2026-04-17T06:23:24.979822"
  },
  "USPTO_solid stat": {
    "ok": false,
    "detail": "HTTP 410",
    "ts": "2026-04-17T06:23:25.241411"
  },
  "USPTO_large lang": {
    "ok": false,
    "detail": "HTTP 410",
    "ts": "2026-04-17T06:23:25.496606"
  },
  "USPTO_semiconduc": {
    "ok": false,
    "detail": "HTTP 410",
    "ts": "2026-04-17T06:23:25.739938"
  },
  "USPTO_nuclear fu": {
    "ok": false,
    "detail": "HTTP 410",
    "ts": "2026-04-17T06:23:25.983256"
  },
  "USPTO_mRNA": {
    "ok": false,
    "detail": "HTTP 410",
    "ts": "2026-04-17T06:23:26.224514"
  },
  "USPTO_CRISPR": {
    "ok": false,
    "detail": "HTTP 410",
    "ts": "2026-04-17T06:23:26.465006"
  },
  "USPTO_rare earth": {
    "ok": false,
    "detail": "HTTP 410",
    "ts": "2026-04-17T06:23:26.717574"
  },
  "USPTO_directed e": {
    "ok": false,
    "detail": "HTTP 410",
    "ts": "2026-04-17T06:23:26.958540"
  },
  "USPTO": {
    "ok": false,
    "detail": "",
    "ts": "2026-04-17T06:23:27.159580"
  },
  "EIA": {
    "ok": false,
    "detail": "HTTP 400",
    "ts": "2026-04-17T06:23:28.110489"
  },
  "FED": {
    "ok": true,
    "detail": "HTTP 200",
    "ts": "2026-04-17T06:23:28.208377"
  },
  "ECB": {
    "ok": true,
    "detail": "HTTP 200",
    "ts": "2026-04-17T06:23:28.614807"
  },
  "RBI": {
    "ok": true,
    "detail": "HTTP 200",
    "ts": "2026-04-17T06:23:30.081797"
  },
  "WH": {
    "ok": false,
    "detail": "HTTP 404",
    "ts": "2026-04-17T06:23:30.388575"
  },
  "TREASURY": {
    "ok": false,
    "detail": "HTTPSConnectionPool(host='home.treasury.gov', port=443): Read timed out. (read timeout=10)",
    "ts": "2026-04-17T06:23:40.448966"
  },
  "XINHUA": {
    "ok": false,
    "detail": "HTTP 404",
    "ts": "2026-04-17T06:23:41.477288"
  },
  "KREMLIN": {
    "ok": false,
    "detail": "HTTP 404",
    "ts": "2026-04-17T06:23:42.119436"
  },
  "MEA": {
    "ok": false,
    "detail": "HTTP 403",
    "ts": "2026-04-17T06:23:42.842591"
  },
  "BIS": {
    "ok": false,
    "detail": "HTTP 404",
    "ts": "2026-04-17T06:23:43.282697"
  },
  "LEADERS": {
    "ok": true,
    "detail": "",
    "ts": "2026-04-17T06:23:43.283619"
  },
  "FEDREG": {
    "ok": true,
    "detail": "HTTP 200",
    "ts": "2026-04-17T06:23:43.389032"
  },
  "SEBI": {
    "ok": false,
    "detail": "HTTP 404",
    "ts": "2026-04-17T06:23:44.367104"
  },
  "TGA": {
    "ok": false,
    "detail": "HTTP 404",
    "ts": "2026-04-17T06:23:44.762379"
  },
  "SOFR": {
    "ok": false,
    "detail": "",
    "ts": "2026-04-17T06:23:45.580064"
  },
  "CONGRESS": {
    "ok": false,
    "detail": "HTTP 403",
    "ts": "2026-04-17T06:23:46.045621"
  },
  "INSIDER": {
    "ok": true,
    "detail": "HTTP 200",
    "ts": "2026-04-17T06:23:46.228798"
  },
  "FII_DII": {
    "ok": true,
    "detail": "",
    "ts": "2026-04-17T06:23:47.105825"
  },
  "ETF_FLOWS": {
    "ok": true,
    "detail": "",
    "ts": "2026-04-17T06:23:49.427692"
  },
  "OPTIONS": {
    "ok": true,
    "detail": "Using VIX proxy",
    "ts": "2026-04-17T06:23:49.427713"
  },
  "MARKETS": {
    "ok": true,
    "detail": "73/75",
    "ts": "2026-04-17T06:24:02.665852"
  },
  "FG": {
    "ok": true,
    "detail": "HTTP 200",
    "ts": "2026-04-17T06:24:02.835797"
  },
  "NEWS": {
    "ok": true,
    "detail": "10/17",
    "ts": "2026-04-17T06:24:06.691369"
  },
  "GDELT": {
    "ok": false,
    "detail": "HTTP 429",
    "ts": "2026-04-17T06:24:06.859558"
  },
  "MACRO_CAL": {
    "ok": true,
    "detail": "HTTP 200",
    "ts": "2026-04-17T06:24:06.960079"
  }
}