{
  "WARN_DOL": {
    "ok": false,
    "detail": "HTTP 403",
    "ts": "2026-04-18T08:07:53.019562"
  },
  "WARN_CA": {
    "ok": true,
    "detail": "HTTP 200",
    "ts": "2026-04-18T08:07:57.214681"
  },
  "OFAC": {
    "ok": false,
    "detail": "HTTPSConnectionPool(host='www.treasury.gov', port=443): Read timed out. (read timeout=20)",
    "ts": "2026-04-18T08:08:18.124397"
  },
  "USASPENDING": {
    "ok": true,
    "detail": "",
    "ts": "2026-04-18T08:08:18.321849"
  },
  "USPTO_quantum co": {
    "ok": false,
    "detail": "HTTP 410",
    "ts": "2026-04-18T08:08:18.602265"
  },
  "USPTO_hypersonic": {
    "ok": false,
    "detail": "HTTP 410",
    "ts": "2026-04-18T08:08:19.006973"
  },
  "USPTO_solid stat": {
    "ok": false,
    "detail": "HTTP 410",
    "ts": "2026-04-18T08:08:19.443705"
  },
  "USPTO_large lang": {
    "ok": false,
    "detail": "HTTP 410",
    "ts": "2026-04-18T08:08:19.850627"
  },
  "USPTO_semiconduc": {
    "ok": false,
    "detail": "HTTP 410",
    "ts": "2026-04-18T08:08:20.262422"
  },
  "USPTO_nuclear fu": {
    "ok": false,
    "detail": "HTTP 410",
    "ts": "2026-04-18T08:08:20.686364"
  },
  "USPTO_mRNA": {
    "ok": false,
    "detail": "HTTP 410",
    "ts": "2026-04-18T08:08:21.101147"
  },
  "USPTO_CRISPR": {
    "ok": false,
    "detail": "HTTP 410",
    "ts": "2026-04-18T08:08:21.520730"
  },
  "USPTO_rare earth": {
    "ok": false,
    "detail": "HTTP 410",
    "ts": "2026-04-18T08:08:21.943221"
  },
  "USPTO_directed e": {
    "ok": false,
    "detail": "HTTP 410",
    "ts": "2026-04-18T08:08:22.367096"
  },
  "USPTO": {
    "ok": false,
    "detail": "",
    "ts": "2026-04-18T08:08:22.568103"
  },
  "EIA": {
    "ok": false,
    "detail": "HTTP 400",
    "ts": "2026-04-18T08:08:23.257972"
  },
  "FED": {
    "ok": true,
    "detail": "HTTP 200",
    "ts": "2026-04-18T08:08:23.330681"
  },
  "ECB": {
    "ok": true,
    "detail": "HTTP 200",
    "ts": "2026-04-18T08:08:24.058990"
  },
  "RBI": {
    "ok": true,
    "detail": "HTTP 200",
    "ts": "2026-04-18T08:08:25.551196"
  },
  "WH": {
    "ok": false,
    "detail": "HTTP 404",
    "ts": "2026-04-18T08:08:25.606524"
  },
  "TREASURY": {
    "ok": false,
    "detail": "HTTPSConnectionPool(host='home.treasury.gov', port=443): Read timed out. (read timeout=10)",
    "ts": "2026-04-18T08:08:35.657511"
  },
  "XINHUA": {
    "ok": false,
    "detail": "HTTP 404",
    "ts": "2026-04-18T08:08:36.442679"
  },
  "KREMLIN": {
    "ok": false,
    "detail": "HTTP 404",
    "ts": "2026-04-18T08:08:37.385374"
  },
  "MEA": {
    "ok": false,
    "detail": "HTTP 403",
    "ts": "2026-04-18T08:08:37.973184"
  },
  "BIS": {
    "ok": false,
    "detail": "HTTP 404",
    "ts": "2026-04-18T08:08:38.651184"
  },
  "LEADERS": {
    "ok": true,
    "detail": "",
    "ts": "2026-04-18T08:08:38.652036"
  },
  "FEDREG": {
    "ok": true,
    "detail": "HTTP 200",
    "ts": "2026-04-18T08:08:38.896719"
  },
  "SEBI": {
    "ok": false,
    "detail": "HTTP 404",
    "ts": "2026-04-18T08:08:39.850260"
  },
  "TGA": {
    "ok": false,
    "detail": "HTTP 404",
    "ts": "2026-04-18T08:08:40.433991"
  },
  "SOFR": {
    "ok": false,
    "detail": "",
    "ts": "2026-04-18T08:08:41.282212"
  },
  "CONGRESS": {
    "ok": false,
    "detail": "HTTP 403",
    "ts": "2026-04-18T08:08:41.436098"
  },
  "INSIDER": {
    "ok": true,
    "detail": "HTTP 200",
    "ts": "2026-04-18T08:08:41.662385"
  },
  "FII_DII": {
    "ok": true,
    "detail": "",
    "ts": "2026-04-18T08:08:42.452998"
  },
  "ETF_FLOWS": {
    "ok": true,
    "detail": "",
    "ts": "2026-04-18T08:08:44.840578"
  },
  "OPTIONS": {
    "ok": true,
    "detail": "Using VIX proxy",
    "ts": "2026-04-18T08:08:44.840598"
  },
  "MARKETS": {
    "ok": true,
    "detail": "73/75",
    "ts": "2026-04-18T08:09:02.644796"
  },
  "FG": {
    "ok": true,
    "detail": "HTTP 200",
    "ts": "2026-04-18T08:09:02.701704"
  },
  "NEWS": {
    "ok": true,
    "detail": "10/17",
    "ts": "2026-04-18T08:09:06.983837"
  },
  "GDELT": {
    "ok": false,
    "detail": "HTTP 429",
    "ts": "2026-04-18T08:09:10.197022"
  },
  "MACRO_CAL": {
    "ok": true,
    "detail": "HTTP 200",
    "ts": "2026-04-18T08:09:10.257780"
  }
}