{
  "WARN_DOL": {
    "ok": false,
    "detail": "HTTP 403",
    "ts": "2026-05-11T09:26:52.999719"
  },
  "WARN_CA": {
    "ok": true,
    "detail": "HTTP 200",
    "ts": "2026-05-11T09:26:53.315571"
  },
  "OFAC": {
    "ok": false,
    "detail": "HTTPSConnectionPool(host='www.treasury.gov', port=443): Read timed out. (read timeout=20)",
    "ts": "2026-05-11T09:27:14.310867"
  },
  "USASPENDING": {
    "ok": true,
    "detail": "",
    "ts": "2026-05-11T09:27:14.465465"
  },
  "USPTO_quantum co": {
    "ok": true,
    "detail": "HTTP 200",
    "ts": "2026-05-11T09:27:14.814690"
  },
  "USPTO_hypersonic": {
    "ok": true,
    "detail": "HTTP 200",
    "ts": "2026-05-11T09:27:15.137441"
  },
  "USPTO_solid stat": {
    "ok": true,
    "detail": "HTTP 200",
    "ts": "2026-05-11T09:27:15.432157"
  },
  "USPTO_large lang": {
    "ok": true,
    "detail": "HTTP 200",
    "ts": "2026-05-11T09:27:15.743331"
  },
  "USPTO_semiconduc": {
    "ok": true,
    "detail": "HTTP 200",
    "ts": "2026-05-11T09:27:16.039950"
  },
  "USPTO_nuclear fu": {
    "ok": true,
    "detail": "HTTP 200",
    "ts": "2026-05-11T09:27:16.353211"
  },
  "USPTO_mRNA": {
    "ok": true,
    "detail": "HTTP 200",
    "ts": "2026-05-11T09:27:16.663997"
  },
  "USPTO_CRISPR": {
    "ok": true,
    "detail": "HTTP 200",
    "ts": "2026-05-11T09:27:17.007585"
  },
  "USPTO_rare earth": {
    "ok": true,
    "detail": "HTTP 200",
    "ts": "2026-05-11T09:27:17.310161"
  },
  "USPTO_directed e": {
    "ok": true,
    "detail": "HTTP 200",
    "ts": "2026-05-11T09:27:17.618842"
  },
  "USPTO": {
    "ok": false,
    "detail": "",
    "ts": "2026-05-11T09:27:17.620772"
  },
  "EIA": {
    "ok": false,
    "detail": "HTTP 400",
    "ts": "2026-05-11T09:27:18.478932"
  },
  "FED": {
    "ok": true,
    "detail": "HTTP 200",
    "ts": "2026-05-11T09:27:18.540198"
  },
  "ECB": {
    "ok": true,
    "detail": "HTTP 200",
    "ts": "2026-05-11T09:27:19.326499"
  },
  "RBI": {
    "ok": true,
    "detail": "HTTP 200",
    "ts": "2026-05-11T09:27:20.779067"
  },
  "WH": {
    "ok": false,
    "detail": "HTTP 404",
    "ts": "2026-05-11T09:27:20.838589"
  },
  "TREASURY": {
    "ok": false,
    "detail": "HTTPSConnectionPool(host='home.treasury.gov', port=443): Read timed out. (read timeout=10)",
    "ts": "2026-05-11T09:27:30.918066"
  },
  "XINHUA": {
    "ok": false,
    "detail": "HTTP 404",
    "ts": "2026-05-11T09:27:31.602040"
  },
  "KREMLIN": {
    "ok": false,
    "detail": "HTTP 404",
    "ts": "2026-05-11T09:27:32.389448"
  },
  "MEA": {
    "ok": false,
    "detail": "HTTP 403",
    "ts": "2026-05-11T09:27:32.713333"
  },
  "BIS": {
    "ok": false,
    "detail": "HTTP 404",
    "ts": "2026-05-11T09:27:33.752587"
  },
  "LEADERS": {
    "ok": true,
    "detail": "",
    "ts": "2026-05-11T09:27:33.753416"
  },
  "FEDREG": {
    "ok": true,
    "detail": "HTTP 200",
    "ts": "2026-05-11T09:27:34.003418"
  },
  "SEBI": {
    "ok": false,
    "detail": "HTTP 404",
    "ts": "2026-05-11T09:27:35.384806"
  },
  "TGA": {
    "ok": false,
    "detail": "HTTP 404",
    "ts": "2026-05-11T09:27:35.944133"
  },
  "SOFR": {
    "ok": false,
    "detail": "",
    "ts": "2026-05-11T09:27:36.757923"
  },
  "CONGRESS": {
    "ok": false,
    "detail": "HTTP 403",
    "ts": "2026-05-11T09:27:36.908370"
  },
  "INSIDER": {
    "ok": true,
    "detail": "HTTP 200",
    "ts": "2026-05-11T09:27:37.133376"
  },
  "FII_DII": {
    "ok": true,
    "detail": "",
    "ts": "2026-05-11T09:27:37.945546"
  },
  "ETF_FLOWS": {
    "ok": true,
    "detail": "",
    "ts": "2026-05-11T09:27:40.404350"
  },
  "OPTIONS": {
    "ok": true,
    "detail": "Using VIX proxy",
    "ts": "2026-05-11T09:27:40.404369"
  },
  "MARKETS": {
    "ok": true,
    "detail": "73/75",
    "ts": "2026-05-11T09:28:02.340223"
  },
  "FG": {
    "ok": true,
    "detail": "HTTP 200",
    "ts": "2026-05-11T09:28:02.398157"
  },
  "NEWS": {
    "ok": true,
    "detail": "10/17",
    "ts": "2026-05-11T09:28:07.902545"
  },
  "GDELT": {
    "ok": false,
    "detail": "HTTP 429",
    "ts": "2026-05-11T09:28:12.981360"
  },
  "MACRO_CAL": {
    "ok": true,
    "detail": "HTTP 200",
    "ts": "2026-05-11T09:28:13.050672"
  }
}