{
  "WARN_DOL": {
    "ok": false,
    "detail": "HTTP 403",
    "ts": "2026-05-02T18:45:07.945808"
  },
  "WARN_CA": {
    "ok": true,
    "detail": "HTTP 200",
    "ts": "2026-05-02T18:45:08.649980"
  },
  "OFAC": {
    "ok": false,
    "detail": "HTTPSConnectionPool(host='www.treasury.gov', port=443): Read timed out. (read timeout=20)",
    "ts": "2026-05-02T18:45:29.407013"
  },
  "USASPENDING": {
    "ok": true,
    "detail": "",
    "ts": "2026-05-02T18:45:29.729452"
  },
  "USPTO_quantum co": {
    "ok": true,
    "detail": "HTTP 200",
    "ts": "2026-05-02T18:45:30.062879"
  },
  "USPTO_hypersonic": {
    "ok": true,
    "detail": "HTTP 200",
    "ts": "2026-05-02T18:45:30.257806"
  },
  "USPTO_solid stat": {
    "ok": true,
    "detail": "HTTP 200",
    "ts": "2026-05-02T18:45:30.503666"
  },
  "USPTO_large lang": {
    "ok": true,
    "detail": "HTTP 200",
    "ts": "2026-05-02T18:45:30.727131"
  },
  "USPTO_semiconduc": {
    "ok": true,
    "detail": "HTTP 200",
    "ts": "2026-05-02T18:45:30.916900"
  },
  "USPTO_nuclear fu": {
    "ok": true,
    "detail": "HTTP 200",
    "ts": "2026-05-02T18:45:31.108032"
  },
  "USPTO_mRNA": {
    "ok": true,
    "detail": "HTTP 200",
    "ts": "2026-05-02T18:45:31.330744"
  },
  "USPTO_CRISPR": {
    "ok": true,
    "detail": "HTTP 200",
    "ts": "2026-05-02T18:45:31.540800"
  },
  "USPTO_rare earth": {
    "ok": true,
    "detail": "HTTP 200",
    "ts": "2026-05-02T18:45:31.817946"
  },
  "USPTO_directed e": {
    "ok": true,
    "detail": "HTTP 200",
    "ts": "2026-05-02T18:45:32.001515"
  },
  "USPTO": {
    "ok": false,
    "detail": "",
    "ts": "2026-05-02T18:45:32.003546"
  },
  "EIA": {
    "ok": false,
    "detail": "HTTP 400",
    "ts": "2026-05-02T18:45:33.002845"
  },
  "FED": {
    "ok": true,
    "detail": "HTTP 200",
    "ts": "2026-05-02T18:45:33.093241"
  },
  "ECB": {
    "ok": true,
    "detail": "HTTP 200",
    "ts": "2026-05-02T18:45:33.585484"
  },
  "RBI": {
    "ok": true,
    "detail": "HTTP 200",
    "ts": "2026-05-02T18:45:35.038991"
  },
  "WH": {
    "ok": false,
    "detail": "HTTP 404",
    "ts": "2026-05-02T18:45:35.501732"
  },
  "TREASURY": {
    "ok": false,
    "detail": "HTTPSConnectionPool(host='home.treasury.gov', port=443): Read timed out. (read timeout=10)",
    "ts": "2026-05-02T18:45:45.645132"
  },
  "XINHUA": {
    "ok": false,
    "detail": "HTTP 404",
    "ts": "2026-05-02T18:45:46.419234"
  },
  "KREMLIN": {
    "ok": false,
    "detail": "HTTP 404",
    "ts": "2026-05-02T18:45:46.907819"
  },
  "MEA": {
    "ok": false,
    "detail": "HTTP 403",
    "ts": "2026-05-02T18:45:47.563748"
  },
  "BIS": {
    "ok": false,
    "detail": "HTTP 404",
    "ts": "2026-05-02T18:45:48.222779"
  },
  "LEADERS": {
    "ok": true,
    "detail": "",
    "ts": "2026-05-02T18:45:48.223474"
  },
  "FEDREG": {
    "ok": true,
    "detail": "HTTP 200",
    "ts": "2026-05-02T18:45:48.392927"
  },
  "SEBI": {
    "ok": false,
    "detail": "HTTP 404",
    "ts": "2026-05-02T18:45:49.306964"
  },
  "TGA": {
    "ok": false,
    "detail": "HTTP 404",
    "ts": "2026-05-02T18:45:49.715630"
  },
  "SOFR": {
    "ok": false,
    "detail": "",
    "ts": "2026-05-02T18:45:50.791279"
  },
  "CONGRESS": {
    "ok": false,
    "detail": "HTTP 403",
    "ts": "2026-05-02T18:45:51.115436"
  },
  "INSIDER": {
    "ok": true,
    "detail": "HTTP 200",
    "ts": "2026-05-02T18:45:51.227292"
  },
  "FII_DII": {
    "ok": true,
    "detail": "",
    "ts": "2026-05-02T18:45:52.307590"
  },
  "ETF_FLOWS": {
    "ok": true,
    "detail": "",
    "ts": "2026-05-02T18:45:55.039659"
  },
  "OPTIONS": {
    "ok": true,
    "detail": "Using VIX proxy",
    "ts": "2026-05-02T18:45:55.039677"
  },
  "MARKETS": {
    "ok": true,
    "detail": "73/75",
    "ts": "2026-05-02T18:46:07.878092"
  },
  "FG": {
    "ok": true,
    "detail": "HTTP 200",
    "ts": "2026-05-02T18:46:07.984054"
  },
  "NEWS": {
    "ok": true,
    "detail": "10/17",
    "ts": "2026-05-02T18:46:13.026408"
  },
  "GDELT": {
    "ok": false,
    "detail": "HTTPSConnectionPool(host='api.gdeltproject.org', port=443): Read timed out. (read timeout=14)",
    "ts": "2026-05-02T18:46:30.364405"
  },
  "MACRO_CAL": {
    "ok": true,
    "detail": "HTTP 200",
    "ts": "2026-05-02T18:46:30.427333"
  }
}