{
  "WARN_DOL": {
    "ok": false,
    "detail": "HTTP 403",
    "ts": "2026-05-14T02:28:28.066845"
  },
  "WARN_CA": {
    "ok": true,
    "detail": "HTTP 200",
    "ts": "2026-05-14T02:28:28.777793"
  },
  "OFAC": {
    "ok": false,
    "detail": "HTTPSConnectionPool(host='www.treasury.gov', port=443): Read timed out. (read timeout=20)",
    "ts": "2026-05-14T02:28:49.766025"
  },
  "USASPENDING": {
    "ok": true,
    "detail": "",
    "ts": "2026-05-14T02:28:50.106214"
  },
  "USPTO_quantum co": {
    "ok": true,
    "detail": "HTTP 200",
    "ts": "2026-05-14T02:28:50.482245"
  },
  "USPTO_hypersonic": {
    "ok": true,
    "detail": "HTTP 200",
    "ts": "2026-05-14T02:28:50.682821"
  },
  "USPTO_solid stat": {
    "ok": true,
    "detail": "HTTP 200",
    "ts": "2026-05-14T02:28:50.948155"
  },
  "USPTO_large lang": {
    "ok": true,
    "detail": "HTTP 200",
    "ts": "2026-05-14T02:28:51.125244"
  },
  "USPTO_semiconduc": {
    "ok": true,
    "detail": "HTTP 200",
    "ts": "2026-05-14T02:28:51.319043"
  },
  "USPTO_nuclear fu": {
    "ok": true,
    "detail": "HTTP 200",
    "ts": "2026-05-14T02:28:51.515945"
  },
  "USPTO_mRNA": {
    "ok": true,
    "detail": "HTTP 200",
    "ts": "2026-05-14T02:28:51.743397"
  },
  "USPTO_CRISPR": {
    "ok": true,
    "detail": "HTTP 200",
    "ts": "2026-05-14T02:28:51.960038"
  },
  "USPTO_rare earth": {
    "ok": true,
    "detail": "HTTP 200",
    "ts": "2026-05-14T02:28:52.137625"
  },
  "USPTO_directed e": {
    "ok": true,
    "detail": "HTTP 200",
    "ts": "2026-05-14T02:28:52.329747"
  },
  "USPTO": {
    "ok": false,
    "detail": "",
    "ts": "2026-05-14T02:28:52.331971"
  },
  "EIA": {
    "ok": false,
    "detail": "HTTP 400",
    "ts": "2026-05-14T02:28:53.417858"
  },
  "FED": {
    "ok": true,
    "detail": "HTTP 200",
    "ts": "2026-05-14T02:28:53.489704"
  },
  "ECB": {
    "ok": true,
    "detail": "HTTP 200",
    "ts": "2026-05-14T02:28:54.023707"
  },
  "RBI": {
    "ok": true,
    "detail": "HTTP 200",
    "ts": "2026-05-14T02:28:55.958299"
  },
  "WH": {
    "ok": false,
    "detail": "HTTP 404",
    "ts": "2026-05-14T02:28:56.104713"
  },
  "TREASURY": {
    "ok": false,
    "detail": "HTTPSConnectionPool(host='home.treasury.gov', port=443): Read timed out. (read timeout=10)",
    "ts": "2026-05-14T02:29:06.264430"
  },
  "XINHUA": {
    "ok": false,
    "detail": "HTTP 404",
    "ts": "2026-05-14T02:29:06.918784"
  },
  "KREMLIN": {
    "ok": false,
    "detail": "HTTP 404",
    "ts": "2026-05-14T02:29:07.505460"
  },
  "MEA": {
    "ok": false,
    "detail": "HTTP 403",
    "ts": "2026-05-14T02:29:08.157386"
  },
  "BIS": {
    "ok": false,
    "detail": "HTTP 404",
    "ts": "2026-05-14T02:29:08.912262"
  },
  "LEADERS": {
    "ok": true,
    "detail": "",
    "ts": "2026-05-14T02:29:08.912927"
  },
  "FEDREG": {
    "ok": true,
    "detail": "HTTP 200",
    "ts": "2026-05-14T02:29:09.053200"
  },
  "SEBI": {
    "ok": false,
    "detail": "HTTP 404",
    "ts": "2026-05-14T02:29:10.462838"
  },
  "TGA": {
    "ok": false,
    "detail": "HTTP 404",
    "ts": "2026-05-14T02:29:10.895528"
  },
  "SOFR": {
    "ok": false,
    "detail": "",
    "ts": "2026-05-14T02:29:12.298262"
  },
  "CONGRESS": {
    "ok": false,
    "detail": "HTTP 403",
    "ts": "2026-05-14T02:29:12.703950"
  },
  "INSIDER": {
    "ok": true,
    "detail": "HTTP 200",
    "ts": "2026-05-14T02:29:12.944379"
  },
  "FII_DII": {
    "ok": true,
    "detail": "",
    "ts": "2026-05-14T02:29:13.903425"
  },
  "ETF_FLOWS": {
    "ok": true,
    "detail": "",
    "ts": "2026-05-14T02:29:17.100849"
  },
  "OPTIONS": {
    "ok": true,
    "detail": "Using VIX proxy",
    "ts": "2026-05-14T02:29:17.100869"
  },
  "MARKETS": {
    "ok": true,
    "detail": "73/75",
    "ts": "2026-05-14T02:29:34.138584"
  },
  "FG": {
    "ok": true,
    "detail": "HTTP 200",
    "ts": "2026-05-14T02:29:34.203541"
  },
  "NEWS": {
    "ok": true,
    "detail": "10/17",
    "ts": "2026-05-14T02:29:38.014469"
  },
  "GDELT": {
    "ok": false,
    "detail": "HTTP 429",
    "ts": "2026-05-14T02:29:38.246779"
  },
  "MACRO_CAL": {
    "ok": true,
    "detail": "HTTP 200",
    "ts": "2026-05-14T02:29:38.321455"
  }
}