{
  "WARN_DOL": {
    "ok": false,
    "detail": "HTTP 403",
    "ts": "2026-06-04T09:44:39.910753"
  },
  "WARN_CA": {
    "ok": true,
    "detail": "HTTP 200",
    "ts": "2026-06-04T09:44:40.795359"
  },
  "OFAC": {
    "ok": false,
    "detail": "HTTPSConnectionPool(host='www.treasury.gov', port=443): Read timed out. (read timeout=20)",
    "ts": "2026-06-04T09:45:01.698313"
  },
  "USASPENDING": {
    "ok": true,
    "detail": "",
    "ts": "2026-06-04T09:45:02.045144"
  },
  "USPTO_quantum co": {
    "ok": true,
    "detail": "HTTP 200",
    "ts": "2026-06-04T09:45:02.552486"
  },
  "USPTO_hypersonic": {
    "ok": true,
    "detail": "HTTP 200",
    "ts": "2026-06-04T09:45:02.776045"
  },
  "USPTO_solid stat": {
    "ok": true,
    "detail": "HTTP 200",
    "ts": "2026-06-04T09:45:03.025902"
  },
  "USPTO_large lang": {
    "ok": true,
    "detail": "HTTP 200",
    "ts": "2026-06-04T09:45:03.229292"
  },
  "USPTO_semiconduc": {
    "ok": true,
    "detail": "HTTP 200",
    "ts": "2026-06-04T09:45:03.342302"
  },
  "USPTO_nuclear fu": {
    "ok": true,
    "detail": "HTTP 200",
    "ts": "2026-06-04T09:45:03.493272"
  },
  "USPTO_mRNA": {
    "ok": true,
    "detail": "HTTP 200",
    "ts": "2026-06-04T09:45:03.599146"
  },
  "USPTO_CRISPR": {
    "ok": true,
    "detail": "HTTP 200",
    "ts": "2026-06-04T09:45:03.695482"
  },
  "USPTO_rare earth": {
    "ok": true,
    "detail": "HTTP 200",
    "ts": "2026-06-04T09:45:03.879783"
  },
  "USPTO_directed e": {
    "ok": true,
    "detail": "HTTP 200",
    "ts": "2026-06-04T09:45:04.059081"
  },
  "USPTO": {
    "ok": false,
    "detail": "",
    "ts": "2026-06-04T09:45:04.061014"
  },
  "EIA": {
    "ok": false,
    "detail": "HTTP 400",
    "ts": "2026-06-04T09:45:05.003788"
  },
  "FED": {
    "ok": true,
    "detail": "HTTP 200",
    "ts": "2026-06-04T09:45:05.060031"
  },
  "ECB": {
    "ok": true,
    "detail": "HTTP 200",
    "ts": "2026-06-04T09:45:05.589131"
  },
  "RBI": {
    "ok": true,
    "detail": "HTTP 200",
    "ts": "2026-06-04T09:45:07.268625"
  },
  "WH": {
    "ok": false,
    "detail": "HTTP 404",
    "ts": "2026-06-04T09:45:07.510164"
  },
  "TREASURY": {
    "ok": false,
    "detail": "HTTPSConnectionPool(host='home.treasury.gov', port=443): Read timed out. (read timeout=10)",
    "ts": "2026-06-04T09:45:17.618566"
  },
  "XINHUA": {
    "ok": false,
    "detail": "HTTP 404",
    "ts": "2026-06-04T09:45:18.475405"
  },
  "KREMLIN": {
    "ok": false,
    "detail": "HTTP 404",
    "ts": "2026-06-04T09:45:18.972826"
  },
  "MEA": {
    "ok": true,
    "detail": "HTTP 200",
    "ts": "2026-06-04T09:45:19.979468"
  },
  "BIS": {
    "ok": false,
    "detail": "HTTP 404",
    "ts": "2026-06-04T09:45:20.693183"
  },
  "LEADERS": {
    "ok": true,
    "detail": "",
    "ts": "2026-06-04T09:45:20.694098"
  },
  "FEDREG": {
    "ok": true,
    "detail": "HTTP 200",
    "ts": "2026-06-04T09:45:20.798666"
  },
  "SEBI": {
    "ok": false,
    "detail": "HTTP 404",
    "ts": "2026-06-04T09:45:22.332913"
  },
  "TGA": {
    "ok": false,
    "detail": "HTTP 404",
    "ts": "2026-06-04T09:45:22.774329"
  },
  "SOFR": {
    "ok": false,
    "detail": "",
    "ts": "2026-06-04T09:45:23.613001"
  },
  "CONGRESS": {
    "ok": false,
    "detail": "HTTP 403",
    "ts": "2026-06-04T09:45:23.977468"
  },
  "INSIDER": {
    "ok": true,
    "detail": "HTTP 200",
    "ts": "2026-06-04T09:45:24.167027"
  },
  "FII_DII": {
    "ok": true,
    "detail": "",
    "ts": "2026-06-04T09:45:25.408927"
  },
  "ETF_FLOWS": {
    "ok": true,
    "detail": "",
    "ts": "2026-06-04T09:45:27.866867"
  },
  "OPTIONS": {
    "ok": true,
    "detail": "Using VIX proxy",
    "ts": "2026-06-04T09:45:27.866891"
  },
  "MARKETS": {
    "ok": true,
    "detail": "73/75",
    "ts": "2026-06-04T09:45:40.250086"
  },
  "FG": {
    "ok": true,
    "detail": "HTTP 200",
    "ts": "2026-06-04T09:45:40.340499"
  },
  "NEWS": {
    "ok": true,
    "detail": "10/17",
    "ts": "2026-06-04T09:45:44.707117"
  },
  "GDELT": {
    "ok": false,
    "detail": "HTTP 429",
    "ts": "2026-06-04T09:45:53.554192"
  },
  "MACRO_CAL": {
    "ok": true,
    "detail": "HTTP 200",
    "ts": "2026-06-04T09:45:53.868017"
  }
}