{
  "WARN_DOL": {
    "ok": false,
    "detail": "HTTP 403",
    "ts": "2026-05-01T02:12:45.963287"
  },
  "WARN_CA": {
    "ok": true,
    "detail": "HTTP 200",
    "ts": "2026-05-01T02:12:46.684663"
  },
  "OFAC": {
    "ok": false,
    "detail": "HTTPSConnectionPool(host='www.treasury.gov', port=443): Read timed out. (read timeout=20)",
    "ts": "2026-05-01T02:13:07.859928"
  },
  "USASPENDING": {
    "ok": true,
    "detail": "",
    "ts": "2026-05-01T02:13:08.244810"
  },
  "USPTO_quantum co": {
    "ok": true,
    "detail": "HTTP 200",
    "ts": "2026-05-01T02:13:08.804513"
  },
  "USPTO_hypersonic": {
    "ok": true,
    "detail": "HTTP 200",
    "ts": "2026-05-01T02:13:09.006616"
  },
  "USPTO_solid stat": {
    "ok": true,
    "detail": "HTTP 200",
    "ts": "2026-05-01T02:13:09.135419"
  },
  "USPTO_large lang": {
    "ok": true,
    "detail": "HTTP 200",
    "ts": "2026-05-01T02:13:09.248002"
  },
  "USPTO_semiconduc": {
    "ok": true,
    "detail": "HTTP 200",
    "ts": "2026-05-01T02:13:09.449995"
  },
  "USPTO_nuclear fu": {
    "ok": true,
    "detail": "HTTP 200",
    "ts": "2026-05-01T02:13:09.616112"
  },
  "USPTO_mRNA": {
    "ok": true,
    "detail": "HTTP 200",
    "ts": "2026-05-01T02:13:09.808498"
  },
  "USPTO_CRISPR": {
    "ok": true,
    "detail": "HTTP 200",
    "ts": "2026-05-01T02:13:09.993393"
  },
  "USPTO_rare earth": {
    "ok": true,
    "detail": "HTTP 200",
    "ts": "2026-05-01T02:13:10.152349"
  },
  "USPTO_directed e": {
    "ok": true,
    "detail": "HTTP 200",
    "ts": "2026-05-01T02:13:10.358732"
  },
  "USPTO": {
    "ok": false,
    "detail": "",
    "ts": "2026-05-01T02:13:10.360962"
  },
  "EIA": {
    "ok": false,
    "detail": "HTTP 400",
    "ts": "2026-05-01T02:13:11.418026"
  },
  "FED": {
    "ok": true,
    "detail": "HTTP 200",
    "ts": "2026-05-01T02:13:11.516354"
  },
  "ECB": {
    "ok": true,
    "detail": "HTTP 200",
    "ts": "2026-05-01T02:13:11.926740"
  },
  "RBI": {
    "ok": true,
    "detail": "HTTP 200",
    "ts": "2026-05-01T02:13:13.605681"
  },
  "WH": {
    "ok": false,
    "detail": "HTTP 404",
    "ts": "2026-05-01T02:13:13.650869"
  },
  "TREASURY": {
    "ok": false,
    "detail": "HTTPSConnectionPool(host='home.treasury.gov', port=443): Read timed out. (read timeout=10)",
    "ts": "2026-05-01T02:13:23.774224"
  },
  "XINHUA": {
    "ok": false,
    "detail": "HTTP 404",
    "ts": "2026-05-01T02:13:24.856766"
  },
  "KREMLIN": {
    "ok": false,
    "detail": "HTTP 404",
    "ts": "2026-05-01T02:13:25.500286"
  },
  "MEA": {
    "ok": false,
    "detail": "HTTP 403",
    "ts": "2026-05-01T02:13:26.050052"
  },
  "BIS": {
    "ok": false,
    "detail": "HTTP 404",
    "ts": "2026-05-01T02:13:26.676500"
  },
  "LEADERS": {
    "ok": true,
    "detail": "",
    "ts": "2026-05-01T02:13:26.677320"
  },
  "FEDREG": {
    "ok": true,
    "detail": "HTTP 200",
    "ts": "2026-05-01T02:13:26.778484"
  },
  "SEBI": {
    "ok": false,
    "detail": "HTTP 404",
    "ts": "2026-05-01T02:13:27.784899"
  },
  "TGA": {
    "ok": false,
    "detail": "HTTP 404",
    "ts": "2026-05-01T02:13:28.200358"
  },
  "SOFR": {
    "ok": false,
    "detail": "",
    "ts": "2026-05-01T02:13:28.977045"
  },
  "CONGRESS": {
    "ok": false,
    "detail": "HTTP 403",
    "ts": "2026-05-01T02:13:29.418989"
  },
  "INSIDER": {
    "ok": true,
    "detail": "HTTP 200",
    "ts": "2026-05-01T02:13:29.540946"
  },
  "FII_DII": {
    "ok": true,
    "detail": "",
    "ts": "2026-05-01T02:13:30.284850"
  },
  "ETF_FLOWS": {
    "ok": true,
    "detail": "",
    "ts": "2026-05-01T02:13:32.681405"
  },
  "OPTIONS": {
    "ok": true,
    "detail": "Using VIX proxy",
    "ts": "2026-05-01T02:13:32.681427"
  },
  "MARKETS": {
    "ok": true,
    "detail": "73/75",
    "ts": "2026-05-01T02:13:44.986011"
  },
  "FG": {
    "ok": true,
    "detail": "HTTP 200",
    "ts": "2026-05-01T02:13:45.041053"
  },
  "NEWS": {
    "ok": true,
    "detail": "10/17",
    "ts": "2026-05-01T02:13:49.513711"
  },
  "GDELT": {
    "ok": false,
    "detail": "HTTP 429",
    "ts": "2026-05-01T02:13:50.406762"
  },
  "MACRO_CAL": {
    "ok": true,
    "detail": "HTTP 200",
    "ts": "2026-05-01T02:13:50.463490"
  }
}